pretty_downloader/__init__.py
pretty_downloader/pretty_downloader.py
pretty_downloader-0.2.0.dist-info/LICENSE
pretty_downloader-0.2.0.dist-info/METADATA
pretty_downloader-0.2.0.dist-info/WHEEL
pretty_downloader-0.2.0.dist-info/top_level.txt
pretty_downloader-0.2.0.dist-info/RECORD
