Metadata-Version: 2.1
Name: pretty-downloader
Version: 0.2.0
Summary: This is a simple python pretty downloader for your projects.
Home-page: https://github.com/DEADSEC-SECURITY/pretty-downloader
Author: DeadSec-Security
Author-email: amng835@gmail.com
License: MIT
Keywords: progressbar,downloader,download,console,bar,progress,download-bar
Platform: UNKNOWN
Requires-Python: >=3.7
License-File: LICENSE
Requires-Dist: tqdm (==4.57.0)
Requires-Dist: requests (==2.25.1)
